oliv/__init__.py
oliv/cross_section.py
oliv/image_processing.py
oliv/motion.py
oliv/ortho.py
oliv/plot.py
oliv/post_processing.py
oliv/stabilisation.py
oliv/utils.py
oliv/video.py
oliv/common/__init__.py
oliv/common/base.py
oliv/common/spatial.py
oliv/image/__init__.py
oliv/image/framestack.py
oliv/image/mask.py
oliv/image/processing.py
oliv/image/videofile.py
oliv/lib_fortran/ortho_gfort13.3.so
oliv/lib_fortran/ortho_win11.dll
oliv/lib_fortran/piv_gfort13.3.so
oliv/lib_fortran/piv_win11.dll
oliv/lib_fortran/q_compute_gfort13.3.so
oliv/lib_fortran/wrapper_ortho.py
oliv/lib_fortran/wrapper_piv.py
oliv/lib_fortran/wrapper_q_compute.py
oliv/projection/__init__.py
oliv/projection/base.py
oliv/projection/dlt.py
oliv/projection/grp.py
oliv/section/__init__.py
oliv/section/bathymetry.py
oliv/section/results.py
oliv/stab/__init__.py
oliv/stab/base.py
oliv/stab/gray_stab.py
oliv/velocimetry/__init__.py
oliv/velocimetry/aggregation.py
oliv/velocimetry/grid.py
oliv/velocimetry/io.py
oliv/velocimetry/velocimetry_results.py
oliv/velocimetry/filters/__init__.py
oliv/velocimetry/filters/base.py
oliv/velocimetry/filters/correlation_thresold.py
oliv/velocimetry/filters/median_test.py
oliv/velocimetry/filters/velocity_angle_temporal_consistency.py
oliv/velocimetry/filters/velocity_temporal_consistency.py
oliv/velocimetry/filters/velocity_threshold.py
oliv-1.1.1.dist-info/licenses/LICENSE
oliv-1.1.1.dist-info/METADATA
oliv-1.1.1.dist-info/WHEEL
oliv-1.1.1.dist-info/top_level.txt
oliv-1.1.1.dist-info/RECORD
