Metadata-Version: 2.4
Name: OLIV
Version: 1.1.1
Summary: Open Library for Image Velocimetry
Author-email: Pierre Horgue <pierre.horgue@toulouse-inp.fr>
Project-URL: Documentation, https://oliv.readthedocs.io/en/main/
Project-URL: Repository, https://gitlab.com/image-velocimetry/oliv
Classifier: License :: OSI Approved :: GNU General Public License v3 or later (GPLv3+)
Classifier: Programming Language :: Python :: 3.12
Requires-Python: >=3.12
License-File: LICENSE
Requires-Dist: opencv-python>=4.12.0.88
Requires-Dist: scipy>=1.16.2
Requires-Dist: matplotlib>=3.10.6
Requires-Dist: progress>=1.6.1
Dynamic: license-file
